excelsheet/__init__.py
excelsheet/dataframe.py
excelsheet/file.py
excelsheet/utils.py
excelsheet-0.1.4.dist-info/METADATA
excelsheet-0.1.4.dist-info/WHEEL
excelsheet-0.1.4.dist-info/licenses/LICENSE
excelsheet-0.1.4.dist-info/RECORD
