Metadata-Version: 2.4
Name: excelsheet
Version: 0.1.4
Summary: Unified API to read/save Excel sheet files (.xlsx, .xls, etc.) using multiple backends (pandas, openpyxl, pywin32, etc.).
Project-URL: homepage, https://github.com/danyalziakhan/excelsheet
Author-email: Danyal Zia Khan <danyalziakhan@gmail.com>
License-Expression: MIT
License-File: LICENSE
Classifier: Development Status :: 5 - Production/Stable
Classifier: Environment :: Other Environment
Classifier: Intended Audience :: Developers
Classifier: License :: OSI Approved :: MIT License
Classifier: Operating System :: OS Independent
Classifier: Programming Language :: Python :: 3
Classifier: Programming Language :: Python :: 3.10
Classifier: Programming Language :: Python :: 3.11
Classifier: Programming Language :: Python :: 3.12
Classifier: Programming Language :: Python :: 3.13
Classifier: Programming Language :: Python :: Implementation :: CPython
Classifier: Topic :: Software Development :: Libraries :: Python Modules
Requires-Python: <3.14,>=3.10
Requires-Dist: openpyxl<4,>=3.1.2
Requires-Dist: pandas<3,>=2.2.2
Requires-Dist: pywin32>=306
